alastria_auth/__init__.py
alastria_auth/abstractions.py
alastria_auth/admin.py
alastria_auth/apps.py
alastria_auth/decorators.py
alastria_auth/enums.py
alastria_auth/middleware.py
alastria_auth/models.py
alastria_auth/serializers.py
alastria_auth/service.py
alastria_auth/tests.py
alastria_auth/urls.py
alastria_auth/views.py
alastria_auth/migrations/0001_initial.py
alastria_auth/migrations/0002_apisession_request_session_id_and_more.py
alastria_auth/migrations/0003_apisession_extra_info_and_more.py
alastria_auth/migrations/0004_alter_apisession_expiration_date_and_more.py
alastria_auth/migrations/__init__.py
alastria_auth-0.0.17.dist-info/LICENSE
alastria_auth-0.0.17.dist-info/METADATA
alastria_auth-0.0.17.dist-info/WHEEL
alastria_auth-0.0.17.dist-info/top_level.txt
alastria_auth-0.0.17.dist-info/RECORD
