Metadata-Version: 2.1
Name: alastria-auth
Version: 0.0.17
Summary: A small alastria_auth app for django
Author-email: Alejandro <agarrido@izertis.com>
Classifier: Programming Language :: Python :: 3
Classifier: License :: OSI Approved :: MIT License
Classifier: Operating System :: OS Independent
Requires-Python: >=3.7
License-File: LICENSE
Requires-Dist: alastria-identity
Requires-Dist: Django (==4.1.3)
Requires-Dist: djangorestframework (==3.14.0)
Requires-Dist: drf-yasg (==1.21.4)
Requires-Dist: pillow (==9.3.0)
Requires-Dist: pyjwt (==2.6.0)
Requires-Dist: qrcode (==7.3.1)
Requires-Dist: web3 (==5.31.3)
Requires-Dist: network-service-client (==0.0.2)
Requires-Dist: alastria-service-client (==0.0.12)
Requires-Dist: django-waffle (==3.0.0)
